autodora/__init__.py
autodora/analyze.py
autodora/cli.py
autodora/experiment.py
autodora/observe.py
autodora/parallel.py
autodora/plot.py
autodora/runner.py
autodora/settings.py
autodora/simple_runner.py
autodora/sql_storage.py
autodora/storage.py
autodora/trajectory.py
autodora/observers/__init__.py
autodora/observers/telegram_observer.py
autodora-0.4.1.dist-info/METADATA
autodora-0.4.1.dist-info/WHEEL
autodora-0.4.1.dist-info/top_level.txt
autodora-0.4.1.dist-info/RECORD
