Metadata-Version: 2.1
Name: autodora
Version: 0.4.1
Summary: Automate experiments and explore your data.
Home-page: http://github.com/samuelkolb/autodora
Author: Samuel Kolb
Author-email: samuel.kolb@me.com
License: MIT
Platform: UNKNOWN
Classifier: License :: OSI Approved :: MIT License
Classifier: Programming Language :: Python
Classifier: Programming Language :: Python :: 3
Requires-Python: >=3.5.0
Requires-Dist: matplotlib
Requires-Dist: peewee
Requires-Dist: pebble
Requires-Dist: numpy
Requires-Dist: temporary
Provides-Extra: telegram
Requires-Dist: python-telegram-bot ; extra == 'telegram'
